skeletonkey/__init__.py
skeletonkey/config.py
skeletonkey/core.py
skeletonkey/instantiate.py
skeletonkey-0.3.2.0.dist-info/licenses/LICENSE
skeletonkey-0.3.2.0.dist-info/METADATA
skeletonkey-0.3.2.0.dist-info/WHEEL
skeletonkey-0.3.2.0.dist-info/top_level.txt
skeletonkey-0.3.2.0.dist-info/RECORD
