Metadata-Version: 2.4
Name: skeletonkey
Version: 0.3.2.0
Summary: A bare-bones configuration managment tool.
Home-page: https://github.com/sizemore0125/skeletonkey
Author: Logan Sizemore
Author-email: sizemore0125@gmail.com
License: MIT
Classifier: License :: OSI Approved :: MIT License
Classifier: Programming Language :: Python :: 3.10
Classifier: Operating System :: OS Independent
Requires-Python: >=3.7
License-File: LICENSE
Requires-Dist: pyYAML>=3.0.0
Dynamic: author
Dynamic: author-email
Dynamic: classifier
Dynamic: description
Dynamic: description-content-type
Dynamic: home-page
Dynamic: license
Dynamic: license-file
Dynamic: requires-dist
Dynamic: requires-python
Dynamic: summary
